cli_ui/__init__.py
cli_ui/py.typed
cli_ui/tests/__init__.py
cli_ui/tests/conftest.py
cli_ui/tests/test_cli_ui.py
cli_ui-0.19.0.dist-info/LICENSE
cli_ui-0.19.0.dist-info/METADATA
cli_ui-0.19.0.dist-info/WHEEL
cli_ui-0.19.0.dist-info/RECORD
