Metadata-Version: 2.3
Name: cli-ui
Version: 0.19.0
Summary: Build Nice User Interfaces In The Terminal
License: BSD-3-Clause
Author: Dimitri Merejkowsky
Author-email: dimitri@dmerej.info
Requires-Python: >=3.9,<4.0
Classifier: License :: OSI Approved :: BSD License
Classifier: Programming Language :: Python :: 3
Classifier: Programming Language :: Python :: 3.9
Classifier: Programming Language :: Python :: 3.10
Classifier: Programming Language :: Python :: 3.11
Classifier: Programming Language :: Python :: 3.12
Classifier: Programming Language :: Python :: 3.13
Requires-Dist: colorama (>=0.4.1,<0.5.0)
Requires-Dist: tabulate (>=0.9.0,<0.10.0)
Requires-Dist: unidecode (>=1.3.6,<2.0.0)
